Swatantracal/__init__.py
Swatantracal/calculator.py
swatantracal-0.1.1.dist-info/METADATA
swatantracal-0.1.1.dist-info/WHEEL
swatantracal-0.1.1.dist-info/entry_points.txt
swatantracal-0.1.1.dist-info/top_level.txt
swatantracal-0.1.1.dist-info/RECORD
